oft_trace/__init__.py
oft_trace/analyzer.py
oft_trace/cli.py
oft_trace/main.py
oft_trace/models.py
oft_trace/parser.py
oft_trace/reporter.py
oft_trace/visualizer.py
oft_trace-0.1.0.dist-info/licenses/LICENSE
oft_trace-0.1.0.dist-info/METADATA
oft_trace-0.1.0.dist-info/WHEEL
oft_trace-0.1.0.dist-info/entry_points.txt
oft_trace-0.1.0.dist-info/top_level.txt
oft_trace-0.1.0.dist-info/RECORD
