Metadata-Version: 2.4
Name: oft-trace
Version: 0.1.0
Summary: Analyzer and visualizer for OpenFastTrace aspec reports
Home-page: https://github.com/vppillai/oft-trace
Author: Vysakh P PIllai
Author-email: vysakhpillai@embeddedinn.com
Classifier: Development Status :: 3 - Alpha
Classifier: Intended Audience :: Developers
Classifier: License :: OSI Approved :: MIT License
Classifier: Programming Language :: Python :: 3
Classifier: Programming Language :: Python :: 3.7
Classifier: Programming Language :: Python :: 3.8
Classifier: Programming Language :: Python :: 3.9
Classifier: Programming Language :: Python :: 3.10
Classifier: Programming Language :: Python :: 3.11
Requires-Python: >=3.7
License-File: LICENSE
Requires-Dist: typer>=0.4.0
Requires-Dist: rich>=10.0.0
Dynamic: author
Dynamic: author-email
Dynamic: classifier
Dynamic: description
Dynamic: description-content-type
Dynamic: home-page
Dynamic: license-file
Dynamic: requires-dist
Dynamic: requires-python
Dynamic: summary
